{
	"$schema": "https://biomejs.dev/schemas/1.9.4/schema.json",
	"vcs": {
		"enabled": true,
		"clientKind": "git",
		"useIgnoreFile": true
	},
	"files": {
		"ignoreUnknown": false,
		"ignore": [
			"node_modules",
			"dist",
			"types",
			"wasm",
			"native",
			"zig-out",
			"zig-cache",
			"target",
			"bench",
			"benchmarks",
			".zig-cache",
			"*.wasm",
			"*.so",
			"*.dll",
			"*.dylib",
			"lib",
			"scripts/dist-address-wasm",
			"docs/.astro",
			"worktrees"
		]
	},
	"formatter": {
		"enabled": true,
		"formatWithErrors": false,
		"indentStyle": "tab",
		"indentWidth": 2,
		"lineWidth": 80,
		"lineEnding": "lf"
	},
	"organizeImports": {
		"enabled": true
	},
	"linter": {
		"enabled": true,
		"rules": {
			"recommended": true,
			"complexity": {
				"noExcessiveCognitiveComplexity": "warn",
				"noForEach": "off"
			},
			"style": {
				"useImportType": "error",
				"useNodejsImportProtocol": "error",
				"noNonNullAssertion": "warn"
			},
			"suspicious": {
				"noExplicitAny": "warn",
				"noConsoleLog": "warn"
			}
		}
	},
	"javascript": {
		"formatter": {
			"quoteStyle": "double",
			"jsxQuoteStyle": "double",
			"quoteProperties": "asNeeded",
			"trailingCommas": "all",
			"semicolons": "always",
			"arrowParentheses": "always",
			"bracketSpacing": true,
			"bracketSameLine": false
		}
	}
}
